AUTHORS.rst
CONTRIBUTING.rst
HISTORY.rst
LICENSE
MANIFEST.in
README.rst
setup.cfg
setup.py
djangoblockchain_info/__init__.py
djangoblockchain_info/apps.py
djangoblockchain_info/models.py
djangoblockchain_info/urls.py
djangoblockchain_info/views.py
djangoblockchain_info.egg-info/PKG-INFO
djangoblockchain_info.egg-info/SOURCES.txt
djangoblockchain_info.egg-info/dependency_links.txt
djangoblockchain_info.egg-info/not-zip-safe
djangoblockchain_info.egg-info/requires.txt
djangoblockchain_info.egg-info/top_level.txt
djangoblockchain_info/static/css/djangoblockchain_info.css
djangoblockchain_info/static/js/djangoblockchain_info.js
djangoblockchain_info/templates/djangoblockchain_info/base.html