Metadata-Version: 1.1
Name: djangoblockchain-info
Version: 0.1.0
Summary: django package to interact with blockchain.info api
Home-page: https://github.com/b3h3rkz/djangoblockchain-info
Author: Bernard Barje Parah
Author-email: barjebernard@gmail.com
License: MIT
Keywords: djangoblockchain-info
Platform: UNKNOWN
Classifier: Development Status :: 3 - Alpha
Classifier: Framework :: Django
Classifier: Framework :: Django :: 1.8
Classifier: Framework :: Django :: 1.9
Classifier: Framework :: Django :: 1.10
Classifier: Intended Audience :: Developers
Classifier: License :: OSI Approved :: BSD License
Classifier: Natural Language :: English
Classifier: Programming Language :: Python :: 2
Classifier: Programming Language :: Python :: 2.7
Classifier: Programming Language :: Python :: 3
Classifier: Programming Language :: Python :: 3.3
Classifier: Programming Language :: Python :: 3.4
Classifier: Programming Language :: Python :: 3.5
